src/__init__.py
src/dateexpr.py
src/main.py
geotag-0.2.0.dist-info/METADATA
geotag-0.2.0.dist-info/WHEEL
geotag-0.2.0.dist-info/entry_points.txt
geotag-0.2.0.dist-info/RECORD
