Metadata-Version: 2.4
Name: geotag
Version: 0.2.0
Summary: Multithread geotagging of photos using EXIF and GPX data
Author-email: mgt <mgt@oi-wiki.org>
License-Expression: MIT
Keywords: cli,exif,geotag,gpx,photo
Requires-Python: >=3.12
Requires-Dist: tqdm>=4.67.1
